nb_extra/__init__.py
nb_extra/_version.py
nb_extra/surface/__init__.py
nb_extra/surface/_barycentric.c
nb_extra/surface/_barycentric.cpython-311-darwin.so
nb_extra/surface/_barycentric.pyx
nb_extra/surface/barycentric.py
neuroboros_extra-0.1.0.dist-info/LICENSE
neuroboros_extra-0.1.0.dist-info/METADATA
neuroboros_extra-0.1.0.dist-info/WHEEL
neuroboros_extra-0.1.0.dist-info/top_level.txt
neuroboros_extra-0.1.0.dist-info/RECORD
