Metadata-Version: 2.1
Name: neuroboros-extra
Version: 0.1.0
Summary: Cython extensions for neuroboros
Author-email: Ma Feilong <mafeilong@gmail.com>
License: MIT License
Project-URL: Homepage, https://neuroboros.github.io/
Project-URL: Bug Tracker, https://github.com/neuroboros/neuroboros-extra/issues
Classifier: Programming Language :: Python :: 3
Classifier: Programming Language :: Python :: 3 :: Only
Classifier: License :: OSI Approved :: MIT License
Classifier: Operating System :: OS Independent
Classifier: Intended Audience :: Science/Research
Classifier: Topic :: Scientific/Engineering
Requires-Python: >=3.6
License-File: LICENSE
Requires-Dist: numpy
Requires-Dist: scipy
